pinexq/cli/__init__.py
pinexq/cli/__main__.py
pinexq/cli/cmd/__init__.py
pinexq/cli/cmd/cli.py
pinexq/cli/cmd/deploy.py
pinexq/cli/cmd/generate.py
pinexq/cli/cmd/initialization.py
pinexq/cli/cmd/register.py
pinexq/cli/docker_tools/__init__.py
pinexq/cli/docker_tools/client.py
pinexq/cli/pinexq_tools/__init__.py
pinexq/cli/pinexq_tools/client.py
pinexq/cli/pinexq_tools/info.py
pinexq/cli/pinexq_tools/manifest.py
pinexq/cli/pinexq_tools/project.py
pinexq/cli/utils/__init__.py
pinexq/cli/utils/console.py
pinexq/cli/utils/const.py
pinexq/cli/utils/uv_utils.py
pinexq_cli-0.2.0.dist-info/WHEEL
pinexq_cli-0.2.0.dist-info/entry_points.txt
pinexq_cli-0.2.0.dist-info/METADATA
pinexq_cli-0.2.0.dist-info/RECORD
